{
  "workflow": {
    "nodes": [
      {
        "id": "plugin-metadata",
        "type": "modifier",
        "position": {
          "x": 240,
          "y": 160
        },
        "data": {
          "modifier": {
            "name": "Dislocation Analysis",
            "key": "opendxa",
            "icon": "HiCube",
            "author": "Rodolfo Herrera",
            "license": "MIT",
            "version": "1.0.5",
            "homepage": "https://github.com/rodyherrera/Volterra",
            "description": "Analisis de dislocaciones a partir del algoritmo de identificacion de estructura seleccionado por el usuario."
          }
        }
      },
      {
        "id": "plugin-arguments",
        "type": "arguments",
        "position": {
          "x": 528,
          "y": 208
        },
        "data": {
          "arguments": {
            "arguments": [
              {
                "argument": "structure_analysis_plugin",
                "type": "pluginReference",
                "label": "Structure Analysis Algorithm",
                "required": true,
                "showPluginConfiguration": true,
                "pluginReferenceFilterKeys": [
                  "polyhedral-template-matching",
                  "adaptive-common-neighbor-analysis"
                ],
                "pluginReferenceMappings": [
                  {
                    "sourceArgument": "reference_topology",
                    "targetArgument": "crystal_structure",
                    "targetPluginKey": "polyhedral-template-matching",
                    "valueMap": {
                      "fcc": "FCC",
                      "bcc": "BCC",
                      "hcp": "HCP",
                      "sc": "SC",
                      "cubic_diamond": "CUBIC_DIAMOND",
                      "hex_diamond": "HEX_DIAMOND"
                    }
                  },
                  {
                    "sourceArgument": "reference_topology",
                    "targetArgument": "crystal_structure",
                    "targetPluginKey": "adaptive-common-neighbor-analysis",
                    "valueMap": {
                      "fcc": "FCC",
                      "bcc": "BCC",
                      "hcp": "HCP",
                      "sc": "SC",
                      "cubic_diamond": "CUBIC_DIAMOND",
                      "hex_diamond": "HEX_DIAMOND"
                    }
                  }
                ]
              },
              {
                "argument": "reference_topology",
                "type": "select",
                "label": "Reference Topology",
                "default": "fcc",
                "options": [
                  {
                    "key": "fcc",
                    "label": "FCC"
                  },
                  {
                    "key": "bcc",
                    "label": "BCC"
                  },
                  {
                    "key": "hcp",
                    "label": "HCP"
                  },
                  {
                    "key": "sc",
                    "label": "SC"
                  },
                  {
                    "key": "cubic_diamond",
                    "label": "Cubic Diamond"
                  },
                  {
                    "key": "hex_diamond",
                    "label": "Hexagonal Diamond"
                  }
                ]
              },
              {
                "argument": "max_trial_circuit_size",
                "type": "number",
                "label": "Max Trial Circuit Size",
                "default": 14,
                "min": 1,
                "step": 1
              },
              {
                "argument": "circuit_stretchability",
                "type": "number",
                "label": "Circuit Stretchability",
                "default": 9,
                "min": 1,
                "step": 1
              },
              {
                "argument": "line_smoothing_level",
                "type": "number",
                "label": "Line Smoothing Level",
                "default": 1,
                "min": 0,
                "step": 0.1
              },
              {
                "argument": "line_point_interval",
                "type": "number",
                "label": "Line Point Interval",
                "default": 2.5,
                "min": 0,
                "step": 0.1
              }
            ]
          }
        }
      },
      {
        "id": "trajectory-context",
        "type": "context",
        "position": {
          "x": 816,
          "y": 160
        },
        "data": {
          "context": {
            "source": "trajectory_dumps"
          }
        }
      },
      {
        "id": "foreach-trajectory-dumps",
        "type": "forEach",
        "position": {
          "x": 1088,
          "y": 208
        },
        "data": {
          "forEach": {
            "iterableSource": "{{ trajectory-context.trajectory_dumps }}"
          }
        }
      },
      {
        "id": "structure-analysis-plugin",
        "type": "plugin-node",
        "position": {
          "x": 1392,
          "y": 208
        },
        "data": {
          "pluginNode": {
            "executionMode": "argumentReference",
            "argumentReference": "structure_analysis_plugin",
            "outputPathMode": "parent"
          }
        }
      },
      {
        "id": "analysis-entrypoint",
        "type": "entrypoint",
        "position": {
          "x": 1696,
          "y": 208
        },
        "data": {
          "entrypoint": {
            "type": "packaged-executable",
            "binary": "opendxa-plugin.zip",
            "binaryObjectPath": "__UPLOAD_BINARY_OBJECT_PATH__",
            "binaryFileName": "opendxa-plugin.zip",
            "entrypointScript": "bin/opendxa",
            "requirementsFile": "",
            "arguments": "{{ foreach-trajectory-dumps.outputPath }}_annotated.dump {{ foreach-trajectory-dumps.outputPath }} --clusters_table {{ foreach-trajectory-dumps.outputPath }}_clusters.table --clusters_transitions {{ foreach-trajectory-dumps.outputPath }}_cluster_transitions.table --lattice_dir {{ analysis-entrypoint.projectPath }}/share/volt/lattices --export_interface_mesh true --export_structure_identification true --export_coherent_crystalline_regions true {{ plugin-arguments.as_str }}",
            "timeout": -1,
            "inputs": [
              {
                "name": "annotatedDump",
                "required": true,
                "description": "Per-atom annotated LAMMPS dump produced by an upstream structure-identification step."
              },
              {
                "name": "clustersTable",
                "required": true,
                "cliFlag": "--clusters_table",
                "description": "Cluster graph table produced by an upstream structure-identification step (PTM/ACNA/PSM)."
              },
              {
                "name": "clustersTransitions",
                "required": true,
                "cliFlag": "--clusters_transitions",
                "description": "Cluster transitions table produced by an upstream structure-identification step."
              }
            ]
          }
        }
      },
      {
        "id": "primary-exposure",
        "type": "exposure",
        "position": {
          "x": 2016,
          "y": 208
        },
        "data": {
          "exposure": {
            "name": "Dislocations",
            "icon": "HiCube",
            "results": "dislocations.msgpack",
            "iterable": ""
          }
        }
      },
      {
        "id": "primary-export",
        "type": "export",
        "position": {
          "x": 2336,
          "y": 208
        },
        "data": {
          "export": {
            "exporter": "DislocationExporter",
            "type": "glb",
            "options": {
              "lineWidth": 0.8,
              "colorByType": true,
              "material": {
                "metallic": 0,
                "roughness": 0.8,
                "emissive": [
                  0,
                  0,
                  0
                ],
                "baseColor": [
                  1,
                  0.5,
                  0,
                  1
                ]
              }
            }
          }
        }
      },
      {
        "id": "defect-mesh-exposure",
        "type": "exposure",
        "position": {
          "x": 2016,
          "y": 344
        },
        "data": {
          "exposure": {
            "name": "Defect Mesh",
            "icon": "HiCube",
            "results": "defect_mesh.msgpack",
            "iterable": ""
          }
        }
      },
      {
        "id": "defect-mesh-export",
        "type": "export",
        "position": {
          "x": 2336,
          "y": 344
        },
        "data": {
          "export": {
            "exporter": "MeshExporter",
            "type": "glb"
          }
        }
      },
      {
        "id": "interface-mesh-exposure",
        "type": "exposure",
        "position": {
          "x": 2016,
          "y": 480
        },
        "data": {
          "exposure": {
            "name": "Interface Mesh",
            "icon": "HiCube",
            "results": "interface_mesh.msgpack",
            "iterable": ""
          }
        }
      },
      {
        "id": "interface-mesh-export",
        "type": "export",
        "position": {
          "x": 2336,
          "y": 480
        },
        "data": {
          "export": {
            "exporter": "MeshExporter",
            "type": "glb"
          }
        }
      },
      {
        "id": "structure-identification-exposure",
        "type": "exposure",
        "position": {
          "x": 2016,
          "y": 752
        },
        "data": {
          "exposure": {
            "name": "Structure Identification",
            "icon": "HiCube",
            "results": "atoms.msgpack",
            "iterable": ""
          }
        }
      },
      {
        "id": "structure-identification-export",
        "type": "export",
        "position": {
          "x": 2336,
          "y": 752
        },
        "data": {
          "export": {
            "exporter": "AtomisticExporter",
            "type": "glb"
          }
        }
      },
      {
        "id": "crystalline-coherent-regions-exposure",
        "type": "exposure",
        "position": {
          "x": 2016,
          "y": 888
        },
        "data": {
          "exposure": {
            "name": "Crystalline Coherent Regions",
            "icon": "HiCube",
            "results": "coherent_crystalline_regions.msgpack",
            "iterable": ""
          }
        }
      },
      {
        "id": "crystalline-coherent-regions-export",
        "type": "export",
        "position": {
          "x": 2336,
          "y": 888
        },
        "data": {
          "export": {
            "exporter": "AtomisticExporter",
            "type": "glb"
          }
        }
      },
      {
        "id": "burgers-counts-chart-exposure",
        "type": "exposure",
        "position": {
          "x": 1712,
          "y": 848
        },
        "data": {
          "exposure": {
            "name": "Burgers Segment Counts",
            "icon": "HiChartBar",
            "results": "dislocations.msgpack",
            "iterable": "",
            "hasListing": false
          }
        }
      },
      {
        "id": "burgers-counts-chart-export",
        "type": "export",
        "position": {
          "x": 2032,
          "y": 848
        },
        "data": {
          "export": {
            "exporter": "ChartExporter",
            "type": "chart-png",
            "options": {
              "xAxisKey": "burgers_counts.burgers_vector",
              "yAxisKey": "burgers_counts.segment_count",
              "chartType": "bar",
              "title": "Dislocation segments by Burgers vector",
              "xAxisLabel": "Burgers vector",
              "yAxisLabel": "Segments",
              "backgroundColor": "#ffffff",
              "lineColor": "#2563eb",
              "fillColor": "rgba(37, 99, 235, 0.35)",
              "showLegend": false,
              "showGrid": true
            }
          }
        }
      },
      {
        "id": "burgers-lengths-chart-exposure",
        "type": "exposure",
        "position": {
          "x": 1712,
          "y": 976
        },
        "data": {
          "exposure": {
            "name": "Burgers Length Distribution",
            "icon": "HiChartBar",
            "results": "dislocations.msgpack",
            "iterable": "",
            "hasListing": false
          }
        }
      },
      {
        "id": "burgers-lengths-chart-export",
        "type": "export",
        "position": {
          "x": 2032,
          "y": 976
        },
        "data": {
          "export": {
            "exporter": "ChartExporter",
            "type": "chart-png",
            "options": {
              "xAxisKey": "burgers_lengths.burgers_vector",
              "yAxisKey": "burgers_lengths.total_length",
              "chartType": "bar",
              "title": "Dislocation length by Burgers vector",
              "xAxisLabel": "Burgers vector",
              "yAxisLabel": "Total length",
              "backgroundColor": "#ffffff",
              "lineColor": "#16a34a",
              "fillColor": "rgba(22, 163, 74, 0.35)",
              "showLegend": false,
              "showGrid": true
            }
          }
        }
      }
    ],
    "edges": [
      {
        "id": "edge-metadata-arguments",
        "source": "plugin-metadata",
        "sourceHandle": "output",
        "target": "plugin-arguments",
        "targetHandle": "input"
      },
      {
        "id": "edge-arguments-context",
        "source": "plugin-arguments",
        "sourceHandle": "output",
        "target": "trajectory-context",
        "targetHandle": "input"
      },
      {
        "id": "edge-context-foreach",
        "source": "trajectory-context",
        "sourceHandle": "output",
        "target": "foreach-trajectory-dumps",
        "targetHandle": "input"
      },
      {
        "id": "edge-foreach-structure-analysis",
        "source": "foreach-trajectory-dumps",
        "sourceHandle": "output",
        "target": "structure-analysis-plugin",
        "targetHandle": "input"
      },
      {
        "id": "edge-structure-analysis-entrypoint",
        "source": "structure-analysis-plugin",
        "sourceHandle": "output",
        "target": "analysis-entrypoint",
        "targetHandle": "input"
      },
      {
        "id": "edge-entrypoint-primary-exposure",
        "source": "analysis-entrypoint",
        "sourceHandle": "output",
        "target": "primary-exposure",
        "targetHandle": "input"
      },
      {
        "id": "edge-primary-exposure-primary-export",
        "source": "primary-exposure",
        "sourceHandle": "output",
        "target": "primary-export",
        "targetHandle": "input"
      },
      {
        "id": "edge-entrypoint-defect-mesh-exposure",
        "source": "analysis-entrypoint",
        "sourceHandle": "output",
        "target": "defect-mesh-exposure",
        "targetHandle": "input"
      },
      {
        "id": "edge-defect-mesh-exposure-defect-mesh-export",
        "source": "defect-mesh-exposure",
        "sourceHandle": "output",
        "target": "defect-mesh-export",
        "targetHandle": "input"
      },
      {
        "id": "edge-entrypoint-interface-mesh-exposure",
        "source": "analysis-entrypoint",
        "sourceHandle": "output",
        "target": "interface-mesh-exposure",
        "targetHandle": "input"
      },
      {
        "id": "edge-interface-mesh-exposure-interface-mesh-export",
        "source": "interface-mesh-exposure",
        "sourceHandle": "output",
        "target": "interface-mesh-export",
        "targetHandle": "input"
      },
      {
        "id": "edge-entrypoint-structure-identification-exposure",
        "source": "analysis-entrypoint",
        "sourceHandle": "output",
        "target": "structure-identification-exposure",
        "targetHandle": "input"
      },
      {
        "id": "edge-structure-identification-exposure-structure-identification-export",
        "source": "structure-identification-exposure",
        "sourceHandle": "output",
        "target": "structure-identification-export",
        "targetHandle": "input"
      },
      {
        "id": "edge-entrypoint-crystalline-coherent-regions-exposure",
        "source": "analysis-entrypoint",
        "sourceHandle": "output",
        "target": "crystalline-coherent-regions-exposure",
        "targetHandle": "input"
      },
      {
        "id": "edge-crystalline-coherent-regions-exposure-crystalline-coherent-regions-export",
        "source": "crystalline-coherent-regions-exposure",
        "sourceHandle": "output",
        "target": "crystalline-coherent-regions-export",
        "targetHandle": "input"
      },
      {
        "id": "edge-analysis-entrypoint-burgers-counts-chart-exposure",
        "source": "analysis-entrypoint",
        "sourceHandle": "output",
        "target": "burgers-counts-chart-exposure",
        "targetHandle": "input"
      },
      {
        "id": "edge-burgers-counts-chart-exposure-burgers-counts-chart-export",
        "source": "burgers-counts-chart-exposure",
        "sourceHandle": "output",
        "target": "burgers-counts-chart-export",
        "targetHandle": "input"
      },
      {
        "id": "edge-analysis-entrypoint-burgers-lengths-chart-exposure",
        "source": "analysis-entrypoint",
        "sourceHandle": "output",
        "target": "burgers-lengths-chart-exposure",
        "targetHandle": "input"
      },
      {
        "id": "edge-burgers-lengths-chart-exposure-burgers-lengths-chart-export",
        "source": "burgers-lengths-chart-exposure",
        "sourceHandle": "output",
        "target": "burgers-lengths-chart-export",
        "targetHandle": "input"
      }
    ]
  }
}
